{
    "name": "Предметный заземлитель",
    "icon": "naturesaura:pickup_stopper",
    "category": "naturesaura:devices",
    "advancement": "naturesaura:infused_materials",
    "pages": [
        {
            "type": "text",
            "text": "Многие механизмы требуют использования лежащих в мире $(thing)предметов$(), которые легко могут быть подобраны другими игроками, случайно осматривающими механизм.$(br)$(item)Предметный заземлитель$() заставляет предметы в области его работы быть подобранными только в том случае, если они крадутся. Область его действия варьируется от 0 до 8 блоков вокруг него и определяется, относительно, силой примененного к механизму $(item)редстоун сигнала$()."
        },
        {
            "type": "crafting",
            "text": "Создание $(item)Предметный заземлитель$()",
            "recipe": "naturesaura:pickup_stopper"
        }
    ]
}